qsynthesis/__init__.py
qsynthesis/tritonast.py
qsynthesis/types.py
qsynthesis/algorithms/__init__.py
qsynthesis/algorithms/synthesizer_base.py
qsynthesis/algorithms/synthesizer_plhld.py
qsynthesis/algorithms/synthesizer_td.py
qsynthesis/algorithms/synthesizer_tdbu.py
qsynthesis/grammar/__init__.py
qsynthesis/grammar/grammar.py
qsynthesis/grammar/jitting.py
qsynthesis/grammar/ops.py
qsynthesis/plugin/__init__.py
qsynthesis/plugin/actions.py
qsynthesis/plugin/arch.py
qsynthesis/plugin/ast_viewer.py
qsynthesis/plugin/dependencies.py
qsynthesis/plugin/popup_actions.py
qsynthesis/plugin/processor.py
qsynthesis/plugin/slicer.py
qsynthesis/plugin/view.py
qsynthesis/plugin/ui/__init__.py
qsynthesis/plugin/ui/synthesis_ui.py
qsynthesis/tables/__init__.py
qsynthesis/tables/base.py
qsynthesis/tables/lookuptablelvldb.py
qsynthesis/tables/lookuptablerest.py
qsynthesis/utils/__init__.py
qsynthesis/utils/symexec.py
qsynthesis-0.2.0.data/scripts/qsynthesis-table-manager
qsynthesis-0.2.0.data/scripts/qsynthesis-table-server
qsynthesis-0.2.0.dist-info/LICENSE
qsynthesis-0.2.0.dist-info/METADATA
qsynthesis-0.2.0.dist-info/WHEEL
qsynthesis-0.2.0.dist-info/top_level.txt
qsynthesis-0.2.0.dist-info/RECORD
